odoo/addons/shopinvader_validation_token_guest/README.rst
odoo/addons/shopinvader_validation_token_guest/__init__.py
odoo/addons/shopinvader_validation_token_guest/__manifest__.py
odoo/addons/shopinvader_validation_token_guest/i18n/shopinvader_validation_token_guest.pot
odoo/addons/shopinvader_validation_token_guest/models/__init__.py
odoo/addons/shopinvader_validation_token_guest/models/shopinvader_notification.py
odoo/addons/shopinvader_validation_token_guest/models/shopinvader_security_token.py
odoo/addons/shopinvader_validation_token_guest/readme/CONFIGURE.rst
odoo/addons/shopinvader_validation_token_guest/readme/CONTRIBUTORS.rst
odoo/addons/shopinvader_validation_token_guest/readme/DESCRIPTION.rst
odoo/addons/shopinvader_validation_token_guest/static/description/index.html
odoo/addons/shopinvader_validation_token_guest/tests/__init__.py
odoo/addons/shopinvader_validation_token_guest/tests/test_guest_service.py
odoo14_addon_shopinvader_validation_token_guest-14.0.1.0.1.dist-info/METADATA
odoo14_addon_shopinvader_validation_token_guest-14.0.1.0.1.dist-info/WHEEL
odoo14_addon_shopinvader_validation_token_guest-14.0.1.0.1.dist-info/top_level.txt
odoo14_addon_shopinvader_validation_token_guest-14.0.1.0.1.dist-info/RECORD
