Metadata-Version: 2.1
Name: odoo14-addon-shopinvader-validation-token-guest
Version: 14.0.1.0.1
Summary: Apply the security token notification on guest mode too
Home-page: https://github.com/shopinvader/odoo-shopinvader
Author: ACSONE SA/NV
License: AGPL-3
Platform: UNKNOWN
Classifier: Programming Language :: Python
Classifier: Framework :: Odoo
Classifier: Framework :: Odoo :: 14.0
Classifier: License :: OSI Approved :: GNU Affero General Public License v3
Requires-Python: >=3.6
Requires-Dist: odoo14-addon-shopinvader-guest-mode
Requires-Dist: odoo14-addon-shopinvader-validation-token
Requires-Dist: odoo (<14.1dev,>=14.0a)
